{
  "$schema": "https://mintlify.com/schema.json",
  "name": "Swervpay Docs",
  "logo": {
    "dark": "/logo/dark.svg",
    "light": "/logo/light.svg"
  },
  "favicon": "/favicon.svg",
  "colors": {
    "primary": "#654FF0",
    "light": "#654FF0",
    "dark": "#654FF0",
    "anchors": {
      "from": "#0D9373",
      "to": "#654FF0"
    },
    "background": {
      "dark": "#000000",
      "light": "#ffffff"
    }
  },
  "feedback": {
    "thumbsRating": true,
    "suggestEdit": true,
    "raiseIssue": true
  },
  "topbarLinks": [
    {
      "name": "Support",
      "url": "mailto:office@swyftpay.io"
    }
  ],
  "topbarCtaButton": {
    "name": "Dashboard",
    "url": "https://app.swervpay.co"
  },
  "tabs": [
    {
      "name": "API Reference",
      "url": "api-reference"
    },
    {
      "name": "SDKs",
      "url": "sdks"
    }
  ],
  "anchors": [
    {
      "name": "Changelog",
      "icon": "book-open-cover",
      "url": "https://docs.swervpay.co/changelog"
    },
    {
      "name": "Community",
      "icon": "slack",
      "url": "https://swervpay.co/slack"
    },
    {
      "name": "Blog",
      "icon": "newspaper",
      "url": "https://swervpay.co/blog"
    }
  ],
  "navigation": [
    {
      "group": "Get Started",
      "pages": [
        "introduction",
        "authentication",
        "development",
        "go-live-checklist"
      ]
    },
    {
      "group": "Wallet",
      "pages": [
        "wallet/introduction"
      ]
    },
    {
      "group": "Transaction",
      "pages": [
        "transaction/introduction"
      ]
    },
    {
      "group": "Customer",
      "pages": [
        "customer/introduction"
      ]
    },
    {
      "group": "Card",
      "pages": [
        "card/introduction"
      ]
    },
    {
      "group": "FX",
      "pages": [
        "fx/introduction"
      ]
    },
    {
      "group": "Payout",
      "pages": [
        "payout/introduction"
      ]
    },
    {
      "group": "Webhook Events",
      "pages": [
        "webhooks/introduction",
        "webhooks/card",
        "webhooks/customer",
        "webhooks/payout",
        "webhooks/wallet"
      ]
    },
    {
      "group": "API Documentation",
      "pages": [
        "api-reference/introduction"
      ]
    },
    {
      "group": "Customers",
      "pages": [
        "api-reference/customers/get-all-customers",
        "api-reference/customers/get",
        "api-reference/customers/create",
        "api-reference/customers/update",
        "api-reference/customers/kyc",
        "api-reference/customers/blacklist"
      ]
    },
    {
      "group": "FX",
      "pages": [
        "api-reference/fx/get",
        "api-reference/fx/create"
      ]
    },
    {
      "group": "Cards",
      "pages": [
        "api-reference/cards/get-all-cards",
        "api-reference/cards/get",
        "api-reference/cards/create",
        "api-reference/cards/fund-card",
        "api-reference/cards/withdraw-from-card",
        "api-reference/cards/freeze",
        "api-reference/cards/terminate"
      ]
    },
    {
      "group": "Wallets",
      "pages": [
        "api-reference/wallets/get-all-wallets"
      ]
    },
    {
      "group": "Transactions",
      "pages": [
        "api-reference/transactions/get-all-transactions",
        "api-reference/transactions/get"
      ]
    },
    {
      "group": "Payouts",
      "pages": [
        "api-reference/payouts/create",
        "api-reference/payouts/get"
      ]
    },
    {
      "group": "Others",
      "pages": [
        "api-reference/others/get-banks",
        "api-reference/others/resolve-account-number"
      ]
    },
    {
      "group": "Webhook",
      "pages": [
        "api-reference/webhook/test",
        "api-reference/webhook/retry"
      ]
    },
    {
      "group": "SDKs",
      "pages": [
        "sdks/introduction"
      ]
    }
  ],
  "footerSocials": {
    "twitter": "https://twitter.com/swyftpay_io",
    "github": "https://github.com/Swerv-Ltd",
    "linkedin": "https://www.linkedin.com/company/swervltd/"
  }
}